dontbs/__main__.py
dontbs/gh.py
dontbs/goals.json
dontbs/utils.py
dontbs-0.0.5.dist-info/LICENSE
dontbs-0.0.5.dist-info/METADATA
dontbs-0.0.5.dist-info/WHEEL
dontbs-0.0.5.dist-info/entry_points.txt
dontbs-0.0.5.dist-info/top_level.txt
dontbs-0.0.5.dist-info/RECORD
