Metadata-Version: 2.1
Name: dontbs
Version: 0.0.5
Summary: Don't bullshit
Author: Graphity
Project-URL: Homepage, https://github.com/Graphity/dontbs
Project-URL: Bug Tracker, https://github.com/Graphity/dontbs/issues
Classifier: Programming Language :: Python :: 3
Classifier: License :: OSI Approved :: MIT License
Classifier: Operating System :: OS Independent
Requires-Python: >=3.7
License-File: LICENSE
Requires-Dist: requests
Requires-Dist: beautifulsoup4
Requires-Dist: click
